grizzly/__init__.py
grizzly/aggregates.py
grizzly/config.py
grizzly/expression.py
grizzly/generator.py
grizzly/grizzly.yml
grizzly/relationaldbexecutor.py
grizzly/sqlgenerator.py
grizzly/dataframes/__init__.py
grizzly/dataframes/frame.py
grizzly/dataframes/schema.py
grizzly/udfcompiler/__init__.py
grizzly/udfcompiler/test_udfs.py
grizzly/udfcompiler/udfcompiler_exceptions.py
grizzly_sql-0.1.6.dist-info/LICENSE
grizzly_sql-0.1.6.dist-info/METADATA
grizzly_sql-0.1.6.dist-info/WHEEL
grizzly_sql-0.1.6.dist-info/top_level.txt
grizzly_sql-0.1.6.dist-info/RECORD
