Metadata-Version: 2.1
Name: grizzly-sql
Version: 0.1.6
Summary: A Python-to-SQL transpiler to work with relational databases
Home-page: https://github.com/dbis-ilm/grizzly
Author: Databases & Information Systems Group, TU Ilmenau
Author-email: stefan.hagedorn@tu-ilmenau.de
License: MIT
Classifier: Programming Language :: Python :: 3
Classifier: Programming Language :: Python :: 3.6
Classifier: Programming Language :: Python :: 3.7
Classifier: Operating System :: OS Independent
Requires-Python: >=3.6
License-File: LICENSE
